progpy/__init__.py
progpy/composite_model.py
progpy/ensemble_model.py
progpy/exceptions.py
progpy/linear_model.py
progpy/mixture_of_experts.py
progpy/prognostics_model.py
progpy/sim_result.py
progpy/data_models/__init__.py
progpy/data_models/data_model.py
progpy/data_models/dmd.py
progpy/data_models/lstm_model.py
progpy/data_models/pce.py
progpy/datasets/__init__.py
progpy/datasets/nasa_battery.py
progpy/datasets/nasa_cmapss.py
progpy/loading/__init__.py
progpy/loading/controllers.py
progpy/loading/gaussian_wrapper.py
progpy/loading/moving_average.py
progpy/loading/piecewise.py
progpy/metrics/__init__.py
progpy/metrics/samples.py
progpy/metrics/toe_metrics.py
progpy/metrics/toe_profile_metrics.py
progpy/metrics/uncertain_data_metrics.py
progpy/models/__init__.py
progpy/models/battery_circuit.py
progpy/models/battery_electrochem.py
progpy/models/centrifugal_pump.py
progpy/models/dcmotor.py
progpy/models/dcmotor_singlephase.py
progpy/models/esc.py
progpy/models/pneumatic_valve.py
progpy/models/powertrain.py
progpy/models/propeller_load.py
progpy/models/thrown_object.py
progpy/models/aircraft_model/__init__.py
progpy/models/aircraft_model/aircraft.py
progpy/models/aircraft_model/small_rotorcraft.py
progpy/models/aircraft_model/vehicles/__init__.py
progpy/models/aircraft_model/vehicles/vehicles.py
progpy/models/aircraft_model/vehicles/aero/__init__.py
progpy/models/aircraft_model/vehicles/aero/aerodynamics.py
progpy/models/aircraft_model/vehicles/control/__init__.py
progpy/models/aircraft_model/vehicles/control/allocation_functions.py
progpy/models/experimental/__init__.py
progpy/models/experimental/paris_law.py
progpy/models/test_models/__init__.py
progpy/models/test_models/linear_models.py
progpy/models/test_models/linear_thrown_object.py
progpy/models/test_models/other_models.py
progpy/predictors/__init__.py
progpy/predictors/monte_carlo.py
progpy/predictors/prediction.py
progpy/predictors/predictor.py
progpy/predictors/toe_prediction_profile.py
progpy-1.7.1.dist-info/licenses/prog_algs license.pdf
progpy-1.7.1.dist-info/licenses/prog_models license.pdf
progpy-1.7.1.dist-info/METADATA
progpy-1.7.1.dist-info/WHEEL
progpy-1.7.1.dist-info/top_level.txt
progpy-1.7.1.dist-info/RECORD
