Metadata-Version: 2.4
Name: progpy
Version: 1.7.1
Summary: The 2024 NASA Software of the Year, the NASA Prognostic Package (ProgPy) is a python prognostics framework focused on building, using, and evaluating models and algorithms for prognostics (computation of remaining useful life) and health management of engineering systems, and provides a set of prognostics models for select components and prognostics algorithms developed within this framework, including uncertainty propagation.
Author: Matteo Corbetta, Chetan Kulkarni, Portia Banerjee, Jason Watkins, Matthew Daigle
Author-email: Christopher Teubert <christopher.a.teubert@nasa.gov>, Katelyn Griffith <katelyn.j.griffith@nasa.gov>
Maintainer-email: Christopher Teubert <christopher.a.teubert@nasa.gov>, Katelyn Griffith <katelyn.j.griffith@nasa.gov>
License-Expression: NASA-1.3
Project-URL: Homepage, https://nasa.github.io/progpy/
Project-URL: Documentation, https://nasa.github.io/progpy/
Project-URL: Repository, https://github.com/nasa/progpy
Project-URL: Issues, https://github.com/nasa/progpy/issues
Project-URL: Organization, https://www.nasa.gov/content/diagnostics-prognostics
Keywords: prognostics,diagnostics,fault detection,fdir,physics modeling,prognostics and health management,PHM,health management,surrogate modeling,model tuning,simulation,ivhm
Classifier: Development Status :: 5 - Production/Stable
Classifier: Intended Audience :: Science/Research
Classifier: Intended Audience :: Developers
Classifier: Intended Audience :: Manufacturing
Classifier: Topic :: Scientific/Engineering
Classifier: Topic :: Scientific/Engineering :: Artificial Intelligence
Classifier: Topic :: Scientific/Engineering :: Physics
Classifier: Programming Language :: Python :: 3
Classifier: Programming Language :: Python :: 3.7
Classifier: Programming Language :: Python :: 3.8
Classifier: Programming Language :: Python :: 3.9
Classifier: Programming Language :: Python :: 3.10
Classifier: Programming Language :: Python :: 3.11
Classifier: Programming Language :: Python :: 3.12
Classifier: Programming Language :: Python :: 3 :: Only
Requires-Python: <3.13,>=3.7
License-File: prog_models license.pdf
License-File: prog_algs license.pdf
Requires-Dist: scipy
Requires-Dist: pandas
Requires-Dist: matplotlib
Requires-Dist: requests
Requires-Dist: chaospy
Requires-Dist: fastdtw
Requires-Dist: filterpy
Provides-Extra: datadriven
Requires-Dist: tensorflow; (platform_system != "Darwin" or platform_machine != "arm64") and extra == "datadriven"
Requires-Dist: tensorflow-macos; (platform_system == "Darwin" and platform_machine == "arm64") and extra == "datadriven"
Dynamic: license-file
